README.md
setup.py
postman2case/__init__.py
postman2case/cli.py
postman2case/compat.py
postman2case/core.py
postman2case/parser.py
postman2case.egg-info/PKG-INFO
postman2case.egg-info/SOURCES.txt
postman2case.egg-info/dependency_links.txt
postman2case.egg-info/entry_points.txt
postman2case.egg-info/top_level.txt
tests/__init__.py
tests/test_postmanparser.py